anyjson2csv/__init__.py
anyjson2csv/flatten_json.py
anyjson2csv/json_to_csv.py
anyjson2csv-0.0.4.dist-info/LICENSE.txt
anyjson2csv-0.0.4.dist-info/METADATA
anyjson2csv-0.0.4.dist-info/WHEEL
anyjson2csv-0.0.4.dist-info/top_level.txt
anyjson2csv-0.0.4.dist-info/RECORD
