Metadata-Version: 2.1
Name: anyjson2csv
Version: 0.0.4
Summary: JSON flatten for Python
Home-page: https://github.com/mehdiabidi/json2csv
Author: BrainsLogic
Author-email: info@brainslogic.com
License: MIT
Classifier: Development Status :: 4 - Beta
Classifier: Intended Audience :: Developers
Classifier: Topic :: Software Development :: Build Tools
Classifier: License :: OSI Approved :: MIT License
Classifier: Programming Language :: Python :: 3
Requires-Python: >=3.7
License-File: LICENSE.txt
Requires-Dist: pandas
